sphinx_jupyterbook_latex/__init__.py
sphinx_jupyterbook_latex/events.py
sphinx_jupyterbook_latex/nodes.py
sphinx_jupyterbook_latex/py.typed
sphinx_jupyterbook_latex/transforms.py
sphinx_jupyterbook_latex/theme/__init__.py
sphinx_jupyterbook_latex/theme/jupyterBook.cls
sphinx_jupyterbook_latex-0.5.2.dist-info/LICENSE
sphinx_jupyterbook_latex-0.5.2.dist-info/METADATA
sphinx_jupyterbook_latex-0.5.2.dist-info/WHEEL
sphinx_jupyterbook_latex-0.5.2.dist-info/top_level.txt
sphinx_jupyterbook_latex-0.5.2.dist-info/RECORD
