Metadata-Version: 2.1
Name: sphinx_jupyterbook_latex
Version: 0.5.2
Summary: Latex specific features for jupyter book
Home-page: https://executablebooks.org/
Author: Executable Book Project
Author-email: jupyter@googlegroups.com
License: BSD-3-Clause
Platform: UNKNOWN
Classifier: License :: OSI Approved :: BSD License
Classifier: Programming Language :: Python :: 3
Classifier: Programming Language :: Python :: 3 :: Only
Classifier: Programming Language :: Python :: 3.6
Classifier: Programming Language :: Python :: 3.7
Classifier: Programming Language :: Python :: 3.8
Classifier: Programming Language :: Python :: 3.9
Classifier: Programming Language :: Python :: Implementation :: CPython
Requires-Python: >=3.6
Provides-Extra: code_style
Provides-Extra: myst
Provides-Extra: rtd
Provides-Extra: testing
License-File: LICENSE
